es_data_exporter/__init__.py
es_data_exporter/collector.py
es_data_exporter/http.py
es_data_exporter-0.1.4.data/scripts/es_data_exporter
es_data_exporter-0.1.4.dist-info/LICENSE
es_data_exporter-0.1.4.dist-info/METADATA
es_data_exporter-0.1.4.dist-info/WHEEL
es_data_exporter-0.1.4.dist-info/top_level.txt
es_data_exporter-0.1.4.dist-info/RECORD
