Metadata-Version: 2.1
Name: es-data-exporter
Version: 0.1.4
Summary: Elasticsearch data exporter to the Prometheus .
Home-page: https://github.com/yaule/es_data_exporter
Author: kasen
Author-email: kasen@outlook.com
License: MIT
Keywords: prometheus exporter network monitoring elastic search
Platform: UNKNOWN
Classifier: Intended Audience :: Information Technology
Classifier: Intended Audience :: System Administrators
Classifier: License :: OSI Approved :: MIT License
Requires-Dist: pyyaml (>=3.13)
Requires-Dist: requests (>=2.21.0)
Requires-Dist: requests-kerberos (>=0.12.0)
Requires-Dist: pandas (>=0.23.4)
